<output>
  <line>
    <tags>
      <tag class="NNP">XVII</tag>
    </tags>
    <original><![CDATA[XVII.]]></original>
  </line>
  <line>
    <tags/>
    <original><![CDATA[]]></original>
  </line>
  <line>
    <tags>
      <tag class="NNP">Who</tag>
      <tag class="VBD">robbed</tag>
      <tag class="DT">the</tag>
      <tag class="NN">woods</tag>
    </tags>
    <original><![CDATA[Who robbed the woods,]]></original>
  </line>
  <line>
    <tags>
      <tag class="DT">The</tag>
      <tag class="NN">trusting</tag>
      <tag class="NN">woods</tag>
    </tags>
    <original><![CDATA[The trusting woods?]]></original>
  </line>
  <line>
    <tags>
      <tag class="DT">The</tag>
      <tag class="NN">unsuspecting</tag>
      <tag class="NNS">trees</tag>
    </tags>
    <original><![CDATA[The unsuspecting trees]]></original>
  </line>
  <line>
    <tags>
      <tag class="NNP">Brought</tag>
      <tag class="IN">out</tag>
      <tag class="PRP$">their</tag>
      <tag class="NNS">burrs</tag>
      <tag class="CC">and</tag>
      <tag class="NNS">mosses</tag>
    </tags>
    <original><![CDATA[Brought out their burrs and mosses]]></original>
  </line>
  <line>
    <tags>
      <tag class="NNP">His</tag>
      <tag class="NN">fantasy</tag>
      <tag class="TO">to</tag>
      <tag class="NNP">please</tag>
    </tags>
    <original><![CDATA[His fantasy to please.]]></original>
  </line>
  <line>
    <tags>
      <tag class="NNP">He</tag>
      <tag class="VBD">scanned</tag>
      <tag class="PRP$">their</tag>
      <tag class="NN">trinkets</tag>
      <tag class="-NONE-">curious</tag>
    </tags>
    <original><![CDATA[He scanned their trinkets, curious,]]></original>
  </line>
  <line>
    <tags>
      <tag class="PRP">He</tag>
      <tag class="-NONE-">grasped</tag>
      <tag class="PRP">he</tag>
      <tag class="VBP">bore</tag>
      <tag class="NNP">away</tag>
    </tags>
    <original><![CDATA[He grasped, he bore away.]]></original>
  </line>
  <line>
    <tags>
      <tag class="NNP">What</tag>
      <tag class="MD">will</tag>
      <tag class="DT">the</tag>
      <tag class="JJ">solemn</tag>
      <tag class="NN">hemlock</tag>
    </tags>
    <original><![CDATA[What will the solemn hemlock,]]></original>
  </line>
  <line>
    <tags>
      <tag class="WP">What</tag>
      <tag class="MD">will</tag>
      <tag class="DT">the</tag>
      <tag class="JJ">fir-tree</tag>
      <tag class="NN">say</tag>
    </tags>
    <original><![CDATA[What will the fir-tree say?]]></original>
  </line>
</output>
